{
  "nouveaux": [
    {
      "id": 136146,
      "etablissement": {
        "__id": 57085,
        "id": 136146,
        "name": "ASS FOYER JEUNES TRAVA APPRE COMPL ARTIS (AFTAIB)",
        "siret": "30480253100026",
        "siren_unite_legale": null,
        "city": "ANGERS",
        "city_insee_code": "49007",
        "postal_code": "49000",
        "epci": null,
        "epci_lib": null,
        "pat_list": null,
        "pat_lib_list": null,
        "department": null,
        "department_lib": null,
        "region": null,
        "region_lib": null,
        "economic_model": "private",
        "management_type": "direct",
        "production_type": "site",
        "satellite_canteens_count": null,
        "central_producer_siret": null,
        "creation_date": "2026-01-02T13:33:36.162327+01:00",
        "daily_meal_count": 400,
        "yearly_meal_count": 157389,
        "line_ministry": null,
        "modification_date": "2026-01-02T13:33:36.162339+01:00",
        "logo": null,
        "sector_list": "Autres établissements sociaux et médico-sociaux",
        "declaration_donnees_2021": false,
        "declaration_donnees_2022": false,
        "declaration_donnees_2023": false,
        "declaration_donnees_2024": false,
        "active_on_ma_cantine": true
      },
      "ministere": null,
      "region": null
    },
    {
      "id": 136147,
      "etablissement": {
        "__id": 57086,
        "id": 136147,
        "name": "FOYER ST THIBAULT",
        "siret": "78140275500057",
        "siren_unite_legale": null,
        "city": "PARIGNE-LE-POLIN",
        "city_insee_code": "72230",
        "postal_code": "72330",
        "epci": null,
        "epci_lib": null,
        "pat_list": null,
        "pat_lib_list": null,
        "department": null,
        "department_lib": null,
        "region": null,
        "region_lib": null,
        "economic_model": "private",
        "management_type": "conceded",
        "production_type": "site_cooked_elsewhere",
        "satellite_canteens_count": null,
        "central_producer_siret": null,
        "creation_date": "2026-01-03T14:02:09.859499+01:00",
        "daily_meal_count": 42,
        "yearly_meal_count": 15330,
        "line_ministry": null,
        "modification_date": "2026-01-03T14:02:09.859512+01:00",
        "logo": null,
        "sector_list": "EHPAD / maisons de retraite / foyers de personnes âgées",
        "declaration_donnees_2021": false,
        "declaration_donnees_2022": false,
        "declaration_donnees_2023": false,
        "declaration_donnees_2024": false,
        "active_on_ma_cantine": true
      },
      "ministere": null,
      "region": null
    }
  ],
  "modifies": [
    {
      "id": 708,
      "etablissement": {
        "__id": 351,
        "id": 708,
        "name": "UNITE CENTRALE DE RESTAURATION",
        "siret": "26170002500552",
        "siren_unite_legale": null,
        "city": "SAINTES",
        "city_insee_code": "17415",
        "postal_code": "17100",
        "epci": "200036473",
        "epci_lib": "CA \"Saintes - Grandes Rives - L'Agglo\"",
        "pat_list": null,
        "pat_lib_list": null,
        "department": "17",
        "department_lib": "Charente-Maritime",
        "region": "75",
        "region_lib": "Nouvelle-Aquitaine",
        "economic_model": "public",
        "management_type": "direct",
        "production_type": "site",
        "satellite_canteens_count": null,
        "central_producer_siret": null,
        "creation_date": "2021-11-18T15:55:57.076433+01:00",
        "daily_meal_count": 5380,
        "yearly_meal_count": 1410542,
        "line_ministry": null,
        "modification_date": "2026-01-02T13:55:55.796058+01:00",
        "logo": null,
        "sector_list": "Hôpitaux,EHPAD / maisons de retraite / foyers de personnes âgées,Autres établissements sociaux et médico-sociaux",
        "declaration_donnees_2021": true,
        "declaration_donnees_2022": true,
        "declaration_donnees_2023": true,
        "declaration_donnees_2024": true,
        "active_on_ma_cantine": true
      },
      "ministere": null,
      "region": "Nouvelle-Aquitaine",
      "ancienMinistere": null,
      "modifications": [
        {
          "champ": "siret",
          "label": "SIRET",
          "ancienne_valeur": "26170002500339",
          "nouvelle_valeur": "26170002500552"
        },
        {
          "champ": "city",
          "label": "Ville",
          "ancienne_valeur": "Saintes",
          "nouvelle_valeur": "SAINTES"
        },
        {
          "champ": "sector_list",
          "label": "Secteur",
          "ancienne_valeur": "Hôpitaux,Ecole primaire (maternelle et élémentaire),Autres établissements non listés,EHPAD / maisons de retraite / foyers de personnes âgées",
          "nouvelle_valeur": "Hôpitaux,EHPAD / maisons de retraite / foyers de personnes âgées,Autres établissements sociaux et médico-sociaux"
        }
      ]
    },
    {
      "id": 1206,
      "etablissement": {
        "__id": 756,
        "id": 1206,
        "name": "Cantine école Lucie Aubrac",
        "siret": "21310052200019",
        "siren_unite_legale": null,
        "city": "Beaumont-sur-Lèze",
        "city_insee_code": "31052",
        "postal_code": "31870",
        "epci": "200068807",
        "epci_lib": "CC du Bassin Auterivain Haut-Garonnais",
        "pat_list": null,
        "pat_lib_list": null,
        "department": "31",
        "department_lib": "Haute-Garonne",
        "region": "76",
        "region_lib": "Occitanie",
        "economic_model": "public",
        "management_type": "direct",
        "production_type": "site",
        "satellite_canteens_count": null,
        "central_producer_siret": null,
        "creation_date": "2022-02-16T15:52:20.030088+01:00",
        "daily_meal_count": 160,
        "yearly_meal_count": 23040,
        "line_ministry": null,
        "modification_date": "2026-01-02T10:30:36.49713+01:00",
        "logo": null,
        "sector_list": "Ecole primaire (maternelle et élémentaire)",
        "declaration_donnees_2021": false,
        "declaration_donnees_2022": false,
        "declaration_donnees_2023": true,
        "declaration_donnees_2024": true,
        "active_on_ma_cantine": true
      },
      "ministere": null,
      "region": "Occitanie",
      "ancienMinistere": null,
      "modifications": [
        {
          "champ": "yearly_meal_count",
          "label": "Couverts/an",
          "ancienne_valeur": 27400,
          "nouvelle_valeur": 23040
        }
      ]
    },
    {
      "id": 1343,
      "etablissement": {
        "__id": 849,
        "id": 1343,
        "name": "CUISINE CENTRALE SMGT",
        "siret": "25540072300037",
        "siren_unite_legale": null,
        "city": "Toul",
        "city_insee_code": "54528",
        "postal_code": "54200",
        "epci": "200070563",
        "epci_lib": "CC Terres Touloises",
        "pat_list": "1395",
        "pat_lib_list": "PAT Sud meurthe-et-mosellan",
        "department": "54",
        "department_lib": "Meurthe-et-Moselle",
        "region": "44",
        "region_lib": "Grand Est",
        "economic_model": "public",
        "management_type": "direct",
        "production_type": "central_serving",
        "satellite_canteens_count": 35,
        "central_producer_siret": null,
        "creation_date": "2022-03-02T06:17:13.102101+01:00",
        "daily_meal_count": 2000,
        "yearly_meal_count": 409435,
        "line_ministry": null,
        "modification_date": "2026-01-02T09:53:59.554173+01:00",
        "logo": null,
        "sector_list": "Secondaire collège",
        "declaration_donnees_2021": false,
        "declaration_donnees_2022": false,
        "declaration_donnees_2023": true,
        "declaration_donnees_2024": true,
        "active_on_ma_cantine": true
      },
      "ministere": null,
      "region": "Grand Est",
      "ancienMinistere": null,
      "modifications": [
        {
          "champ": "yearly_meal_count",
          "label": "Couverts/an",
          "ancienne_valeur": 372557,
          "nouvelle_valeur": 409435
        }
      ]
    },
    {
      "id": 14613,
      "etablissement": {
        "__id": 6222,
        "id": 14613,
        "name": "ECOLE PRIMAIRE PUBLIQUE",
        "siret": "21720186200026",
        "siren_unite_legale": null,
        "city": "MARESCHE",
        "city_insee_code": "72186",
        "postal_code": "72170",
        "epci": "200072700",
        "epci_lib": "CC Haute Sarthe Alpes Mancelles",
        "pat_list": null,
        "pat_lib_list": null,
        "department": "72",
        "department_lib": "Sarthe",
        "region": "52",
        "region_lib": "Pays de la Loire",
        "economic_model": "public",
        "management_type": "direct",
        "production_type": "site_cooked_elsewhere",
        "satellite_canteens_count": null,
        "central_producer_siret": "53150510500019",
        "creation_date": "2022-07-07T09:10:26.61527+02:00",
        "daily_meal_count": 63,
        "yearly_meal_count": 9129,
        "line_ministry": null,
        "modification_date": "2026-01-02T15:21:42.198698+01:00",
        "logo": null,
        "sector_list": "Ecole primaire (maternelle et élémentaire)",
        "declaration_donnees_2021": false,
        "declaration_donnees_2022": false,
        "declaration_donnees_2023": false,
        "declaration_donnees_2024": true,
        "active_on_ma_cantine": true
      },
      "ministere": null,
      "region": "Pays de la Loire",
      "ancienMinistere": null,
      "modifications": [
        {
          "champ": "name",
          "label": "Nom",
          "ancienne_valeur": "Ecole primaire de Maresche",
          "nouvelle_valeur": "ECOLE PRIMAIRE PUBLIQUE"
        },
        {
          "champ": "city",
          "label": "Ville",
          "ancienne_valeur": "Maresché",
          "nouvelle_valeur": "MARESCHE"
        }
      ]
    },
    {
      "id": 21722,
      "etablissement": {
        "__id": 8190,
        "id": 21722,
        "name": "Ecole élémentaire publique Emilienne et Jacques Kerhoas",
        "siret": "21290053400042",
        "siren_unite_legale": null,
        "city": "Le Faou",
        "city_insee_code": "29053",
        "postal_code": "29590",
        "epci": "200066868",
        "epci_lib": "CC Presqu'île de Crozon-Aulne maritime",
        "pat_list": "1922,1931,5157",
        "pat_lib_list": "PAT de la Communauté de communes de la Presqu'île de Crozon-Aulne Maritime,PAT du Parc naturel régional d'Armorique,PAT du Département du Finistère",
        "department": "29",
        "department_lib": "Finistère",
        "region": "53",
        "region_lib": "Bretagne",
        "economic_model": "public",
        "management_type": "direct",
        "production_type": "site",
        "satellite_canteens_count": null,
        "central_producer_siret": null,
        "creation_date": "2022-08-16T12:24:37.818938+02:00",
        "daily_meal_count": 120,
        "yearly_meal_count": 7612,
        "line_ministry": null,
        "modification_date": "2026-01-02T06:38:30.730805+01:00",
        "logo": "https://cellar-c2.services.clever-cloud.com/ma-cantine-egalim-prod/media/afb76416-9f82-4c0a-8923-8e7bb1d1de08.png",
        "sector_list": "Ecole primaire (maternelle et élémentaire)",
        "declaration_donnees_2021": false,
        "declaration_donnees_2022": false,
        "declaration_donnees_2023": true,
        "declaration_donnees_2024": true,
        "active_on_ma_cantine": true
      },
      "ministere": null,
      "region": "Bretagne",
      "ancienMinistere": null,
      "modifications": [
        {
          "champ": "yearly_meal_count",
          "label": "Couverts/an",
          "ancienne_valeur": 7342,
          "nouvelle_valeur": 7612
        }
      ]
    },
    {
      "id": 22051,
      "etablissement": {
        "__id": 8289,
        "id": 22051,
        "name": "Restaurant Jean Zay",
        "siret": "21350238802346",
        "siren_unite_legale": null,
        "city": "RENNES",
        "city_insee_code": "35238",
        "postal_code": "35000",
        "epci": "243500139",
        "epci_lib": "Rennes Métropole",
        "pat_list": "1659,1663",
        "pat_lib_list": "PAT de la Ville de Rennes,PAT de Rennes Métropole",
        "department": "35",
        "department_lib": "Ille-et-Vilaine",
        "region": "53",
        "region_lib": "Bretagne",
        "economic_model": "public",
        "management_type": "direct",
        "production_type": "site",
        "satellite_canteens_count": null,
        "central_producer_siret": null,
        "creation_date": "2022-08-19T18:32:53.14105+02:00",
        "daily_meal_count": 58,
        "yearly_meal_count": 12461,
        "line_ministry": null,
        "modification_date": "2026-01-02T15:50:34.679352+01:00",
        "logo": null,
        "sector_list": "Restaurants administratifs des collectivités territoriales",
        "declaration_donnees_2021": true,
        "declaration_donnees_2022": true,
        "declaration_donnees_2023": true,
        "declaration_donnees_2024": true,
        "active_on_ma_cantine": true
      },
      "ministere": null,
      "region": "Bretagne",
      "ancienMinistere": null,
      "modifications": [
        {
          "champ": "daily_meal_count",
          "label": "Couverts/jour",
          "ancienne_valeur": 41,
          "nouvelle_valeur": 58
        },
        {
          "champ": "yearly_meal_count",
          "label": "Couverts/an",
          "ancienne_valeur": 9323,
          "nouvelle_valeur": 12461
        },
        {
          "champ": "production_type",
          "label": "Type de production",
          "ancienne_valeur": "site_cooked_elsewhere",
          "nouvelle_valeur": "site"
        }
      ]
    },
    {
      "id": 22052,
      "etablissement": {
        "__id": 8290,
        "id": 22052,
        "name": "Plaine de Baud",
        "siret": "21350238801389",
        "siren_unite_legale": null,
        "city": "RENNES",
        "city_insee_code": "35238",
        "postal_code": "35000",
        "epci": "243500139",
        "epci_lib": "Rennes Métropole",
        "pat_list": "1659,1663",
        "pat_lib_list": "PAT de la Ville de Rennes,PAT de Rennes Métropole",
        "department": "35",
        "department_lib": "Ille-et-Vilaine",
        "region": "53",
        "region_lib": "Bretagne",
        "economic_model": "public",
        "management_type": "direct",
        "production_type": "site",
        "satellite_canteens_count": null,
        "central_producer_siret": null,
        "creation_date": "2022-08-19T18:32:53.167989+02:00",
        "daily_meal_count": 87,
        "yearly_meal_count": 14038,
        "line_ministry": null,
        "modification_date": "2026-01-02T14:45:49.734028+01:00",
        "logo": null,
        "sector_list": "Restaurants administratifs des collectivités territoriales",
        "declaration_donnees_2021": true,
        "declaration_donnees_2022": true,
        "declaration_donnees_2023": true,
        "declaration_donnees_2024": true,
        "active_on_ma_cantine": true
      },
      "ministere": null,
      "region": "Bretagne",
      "ancienMinistere": null,
      "modifications": [
        {
          "champ": "production_type",
          "label": "Type de production",
          "ancienne_valeur": "site_cooked_elsewhere",
          "nouvelle_valeur": "site"
        }
      ]
    },
    {
      "id": 22053,
      "etablissement": {
        "__id": 8291,
        "id": 22053,
        "name": "Restaurant Prévalaye",
        "siret": "21350238800464",
        "siren_unite_legale": null,
        "city": "RENNES",
        "city_insee_code": "35238",
        "postal_code": "35000",
        "epci": "243500139",
        "epci_lib": "Rennes Métropole",
        "pat_list": "1659,1663",
        "pat_lib_list": "PAT de la Ville de Rennes,PAT de Rennes Métropole",
        "department": "35",
        "department_lib": "Ille-et-Vilaine",
        "region": "53",
        "region_lib": "Bretagne",
        "economic_model": "public",
        "management_type": "direct",
        "production_type": "site",
        "satellite_canteens_count": null,
        "central_producer_siret": null,
        "creation_date": "2022-08-19T18:32:53.192936+02:00",
        "daily_meal_count": 23,
        "yearly_meal_count": 5732,
        "line_ministry": null,
        "modification_date": "2026-01-02T16:18:59.226872+01:00",
        "logo": null,
        "sector_list": "Restaurants administratifs des collectivités territoriales",
        "declaration_donnees_2021": true,
        "declaration_donnees_2022": true,
        "declaration_donnees_2023": true,
        "declaration_donnees_2024": true,
        "active_on_ma_cantine": true
      },
      "ministere": null,
      "region": "Bretagne",
      "ancienMinistere": null,
      "modifications": [
        {
          "champ": "daily_meal_count",
          "label": "Couverts/jour",
          "ancienne_valeur": 25,
          "nouvelle_valeur": 23
        },
        {
          "champ": "yearly_meal_count",
          "label": "Couverts/an",
          "ancienne_valeur": 6013,
          "nouvelle_valeur": 5732
        },
        {
          "champ": "production_type",
          "label": "Type de production",
          "ancienne_valeur": "site_cooked_elsewhere",
          "nouvelle_valeur": "site"
        }
      ]
    },
    {
      "id": 22054,
      "etablissement": {
        "__id": 8292,
        "id": 22054,
        "name": "Restaurant Liberté",
        "siret": "21350238800308",
        "siren_unite_legale": null,
        "city": "RENNES",
        "city_insee_code": "35238",
        "postal_code": "35000",
        "epci": "243500139",
        "epci_lib": "Rennes Métropole",
        "pat_list": "1659,1663",
        "pat_lib_list": "PAT de la Ville de Rennes,PAT de Rennes Métropole",
        "department": "35",
        "department_lib": "Ille-et-Vilaine",
        "region": "53",
        "region_lib": "Bretagne",
        "economic_model": "public",
        "management_type": "direct",
        "production_type": "site",
        "satellite_canteens_count": null,
        "central_producer_siret": null,
        "creation_date": "2022-08-19T18:32:53.215111+02:00",
        "daily_meal_count": 60,
        "yearly_meal_count": 9243,
        "line_ministry": null,
        "modification_date": "2026-01-02T16:03:54.061015+01:00",
        "logo": null,
        "sector_list": "Restaurants administratifs des collectivités territoriales",
        "declaration_donnees_2021": true,
        "declaration_donnees_2022": true,
        "declaration_donnees_2023": true,
        "declaration_donnees_2024": true,
        "active_on_ma_cantine": true
      },
      "ministere": null,
      "region": "Bretagne",
      "ancienMinistere": null,
      "modifications": [
        {
          "champ": "daily_meal_count",
          "label": "Couverts/jour",
          "ancienne_valeur": 70,
          "nouvelle_valeur": 60
        },
        {
          "champ": "yearly_meal_count",
          "label": "Couverts/an",
          "ancienne_valeur": 12329,
          "nouvelle_valeur": 9243
        },
        {
          "champ": "production_type",
          "label": "Type de production",
          "ancienne_valeur": "site_cooked_elsewhere",
          "nouvelle_valeur": "site"
        }
      ]
    },
    {
      "id": 23429,
      "etablissement": {
        "__id": 8953,
        "id": 23429,
        "name": "Cantine de Glomel",
        "siret": "21220061200019",
        "siren_unite_legale": null,
        "city": "Glomel",
        "city_insee_code": "22061",
        "postal_code": "22110",
        "epci": "242200715",
        "epci_lib": "CC du Kreiz-Breizh (CCKB)",
        "pat_list": null,
        "pat_lib_list": null,
        "department": "22",
        "department_lib": "Côtes-d'armor",
        "region": "53",
        "region_lib": "Bretagne",
        "economic_model": "public",
        "management_type": "direct",
        "production_type": "site",
        "satellite_canteens_count": null,
        "central_producer_siret": null,
        "creation_date": "2022-09-12T11:44:50.12631+02:00",
        "daily_meal_count": 71,
        "yearly_meal_count": 18254,
        "line_ministry": null,
        "modification_date": "2026-01-02T16:13:01.460174+01:00",
        "logo": "https://cellar-c2.services.clever-cloud.com/ma-cantine-egalim-prod/media/c80622f6-3c28-4d84-97ef-7ed2fea2ca7c.jpeg",
        "sector_list": "Ecole primaire (maternelle et élémentaire),Centre de vacances / sportif",
        "declaration_donnees_2021": false,
        "declaration_donnees_2022": false,
        "declaration_donnees_2023": true,
        "declaration_donnees_2024": true,
        "active_on_ma_cantine": true
      },
      "ministere": null,
      "region": "Bretagne",
      "ancienMinistere": null,
      "modifications": [
        {
          "champ": "daily_meal_count",
          "label": "Couverts/jour",
          "ancienne_valeur": 70,
          "nouvelle_valeur": 71
        },
        {
          "champ": "yearly_meal_count",
          "label": "Couverts/an",
          "ancienne_valeur": 15000,
          "nouvelle_valeur": 18254
        }
      ]
    },
    {
      "id": 28748,
      "etablissement": {
        "__id": 10569,
        "id": 28748,
        "name": "DGAC - SNIA PYRENEES",
        "siret": "13000457500010",
        "siren_unite_legale": null,
        "city": "Paris 20e Arrondissement",
        "city_insee_code": "75120",
        "postal_code": "75020",
        "epci": null,
        "epci_lib": null,
        "pat_list": null,
        "pat_lib_list": null,
        "department": "75",
        "department_lib": "Paris",
        "region": "11",
        "region_lib": "Île-de-France",
        "economic_model": "public",
        "management_type": "direct",
        "production_type": "site",
        "satellite_canteens_count": null,
        "central_producer_siret": null,
        "creation_date": "2022-10-03T15:12:17.306688+02:00",
        "daily_meal_count": 70,
        "yearly_meal_count": 14165,
        "line_ministry": "Environnement",
        "modification_date": "2026-01-03T19:01:46.048506+01:00",
        "logo": null,
        "sector_list": "Restaurants administratifs d'Etat (RA)",
        "declaration_donnees_2021": false,
        "declaration_donnees_2022": false,
        "declaration_donnees_2023": true,
        "declaration_donnees_2024": true,
        "active_on_ma_cantine": true
      },
      "ministere": "Environnement",
      "region": "Île-de-France",
      "ancienMinistere": "Environnement",
      "modifications": [
        {
          "champ": "daily_meal_count",
          "label": "Couverts/jour",
          "ancienne_valeur": 65,
          "nouvelle_valeur": 70
        },
        {
          "champ": "yearly_meal_count",
          "label": "Couverts/an",
          "ancienne_valeur": 14000,
          "nouvelle_valeur": 14165
        }
      ]
    },
    {
      "id": 71935,
      "etablissement": {
        "__id": 21192,
        "id": 71935,
        "name": "COMMUNE DE MERIGNAC",
        "siret": "21160216400017",
        "siren_unite_legale": null,
        "city": "Mérignac",
        "city_insee_code": "16216",
        "postal_code": "16200",
        "epci": "200070514",
        "epci_lib": "CA du Grand Cognac",
        "pat_list": "1488,2736",
        "pat_lib_list": "PAT de la Communauté dAgglomération du Grand Cognac,PAT du Département de Charente",
        "department": "16",
        "department_lib": "Charente",
        "region": "75",
        "region_lib": "Nouvelle-Aquitaine",
        "economic_model": "public",
        "management_type": "direct",
        "production_type": "site",
        "satellite_canteens_count": null,
        "central_producer_siret": null,
        "creation_date": "2023-04-14T11:29:46.227108+02:00",
        "daily_meal_count": 80,
        "yearly_meal_count": 10901,
        "line_ministry": null,
        "modification_date": "2026-01-02T20:30:50.148607+01:00",
        "logo": null,
        "sector_list": "Ecole primaire (maternelle et élémentaire)",
        "declaration_donnees_2021": false,
        "declaration_donnees_2022": true,
        "declaration_donnees_2023": true,
        "declaration_donnees_2024": true,
        "active_on_ma_cantine": true
      },
      "ministere": null,
      "region": "Nouvelle-Aquitaine",
      "ancienMinistere": null,
      "modifications": [
        {
          "champ": "yearly_meal_count",
          "label": "Couverts/an",
          "ancienne_valeur": 9020,
          "nouvelle_valeur": 10901
        }
      ]
    },
    {
      "id": 83739,
      "etablissement": {
        "__id": 25597,
        "id": 83739,
        "name": "Cantine de Arzano",
        "siret": "21290002100016",
        "siren_unite_legale": null,
        "city": "Arzano",
        "city_insee_code": "29002",
        "postal_code": "29300",
        "epci": "242900694",
        "epci_lib": "CA Quimperlé Communauté",
        "pat_list": "1655,5157",
        "pat_lib_list": "Projet Alimentaire de Territoire du Pays de Quimperlé,PAT du Département du Finistère",
        "department": "29",
        "department_lib": "Finistère",
        "region": "53",
        "region_lib": "Bretagne",
        "economic_model": "public",
        "management_type": "direct",
        "production_type": "site",
        "satellite_canteens_count": null,
        "central_producer_siret": null,
        "creation_date": "2024-01-05T09:51:22.648666+01:00",
        "daily_meal_count": 90,
        "yearly_meal_count": 12652,
        "line_ministry": null,
        "modification_date": "2026-01-02T16:15:18.347962+01:00",
        "logo": null,
        "sector_list": "Ecole primaire (maternelle et élémentaire)",
        "declaration_donnees_2021": false,
        "declaration_donnees_2022": false,
        "declaration_donnees_2023": false,
        "declaration_donnees_2024": true,
        "active_on_ma_cantine": true
      },
      "ministere": null,
      "region": "Bretagne",
      "ancienMinistere": null,
      "modifications": [
        {
          "champ": "yearly_meal_count",
          "label": "Couverts/an",
          "ancienne_valeur": 11514,
          "nouvelle_valeur": 12652
        }
      ]
    },
    {
      "id": 85325,
      "etablissement": {
        "__id": 26908,
        "id": 85325,
        "name": "APEI PAPILLONS BLANCS foyer la Ballastière",
        "siret": "78193151400074",
        "siren_unite_legale": null,
        "city": "Libourne",
        "city_insee_code": "33243",
        "postal_code": "33500",
        "epci": "200070092",
        "epci_lib": "CA du Libournais",
        "pat_list": "1501",
        "pat_lib_list": "PAT du Grand Libournais",
        "department": "33",
        "department_lib": "Gironde",
        "region": "75",
        "region_lib": "Nouvelle-Aquitaine",
        "economic_model": "private",
        "management_type": "direct",
        "production_type": "site",
        "satellite_canteens_count": null,
        "central_producer_siret": null,
        "creation_date": "2024-02-25T09:54:44.588629+01:00",
        "daily_meal_count": 90,
        "yearly_meal_count": 30000,
        "line_ministry": null,
        "modification_date": "2026-01-03T10:19:43.2109+01:00",
        "logo": null,
        "sector_list": "Autres établissements sociaux et médico-sociaux",
        "declaration_donnees_2021": false,
        "declaration_donnees_2022": false,
        "declaration_donnees_2023": false,
        "declaration_donnees_2024": true,
        "active_on_ma_cantine": true
      },
      "ministere": null,
      "region": "Nouvelle-Aquitaine",
      "ancienMinistere": null,
      "modifications": [
        {
          "champ": "name",
          "label": "Nom",
          "ancienne_valeur": "APEI PAPILLONS BLANCS",
          "nouvelle_valeur": "APEI PAPILLONS BLANCS foyer la Ballastière"
        }
      ]
    },
    {
      "id": 112736,
      "etablissement": {
        "__id": 39805,
        "id": 112736,
        "name": "Les petits soleils de Saint Etienne du bois",
        "siret": "98186992800052",
        "siren_unite_legale": null,
        "city": "Saint-Étienne-du-Bois",
        "city_insee_code": "85210",
        "postal_code": "85670",
        "epci": "200072882",
        "epci_lib": "CC de Vie et Boulogne",
        "pat_list": null,
        "pat_lib_list": null,
        "department": "85",
        "department_lib": "Vendée",
        "region": "52",
        "region_lib": "Pays de la Loire",
        "economic_model": "private",
        "management_type": "conceded",
        "production_type": "site_cooked_elsewhere",
        "satellite_canteens_count": null,
        "central_producer_siret": "33415947203999",
        "creation_date": "2024-12-19T13:44:49.214031+01:00",
        "daily_meal_count": 5,
        "yearly_meal_count": 600,
        "line_ministry": null,
        "modification_date": "2026-01-01T20:24:07.799442+01:00",
        "logo": null,
        "sector_list": "Crèche",
        "declaration_donnees_2021": false,
        "declaration_donnees_2022": false,
        "declaration_donnees_2023": false,
        "declaration_donnees_2024": false,
        "active_on_ma_cantine": true
      },
      "ministere": null,
      "region": "Pays de la Loire",
      "ancienMinistere": null,
      "modifications": [
        {
          "champ": "daily_meal_count",
          "label": "Couverts/jour",
          "ancienne_valeur": 4,
          "nouvelle_valeur": 5
        },
        {
          "champ": "yearly_meal_count",
          "label": "Couverts/an",
          "ancienne_valeur": 32,
          "nouvelle_valeur": 600
        }
      ]
    },
    {
      "id": 113029,
      "etablissement": {
        "__id": 40030,
        "id": 113029,
        "name": "COMMUNE DE PLESTAN",
        "siret": "21220193300018",
        "siren_unite_legale": null,
        "city": "Plestan",
        "city_insee_code": "22193",
        "postal_code": "22640",
        "epci": "200069391",
        "epci_lib": "CA Lamballe Terre et Mer",
        "pat_list": "1648",
        "pat_lib_list": "PAT de Lamballe Terre et Mer",
        "department": "22",
        "department_lib": "Côtes-d'armor",
        "region": "53",
        "region_lib": "Bretagne",
        "economic_model": "public",
        "management_type": "direct",
        "production_type": "central_serving",
        "satellite_canteens_count": 2,
        "central_producer_siret": null,
        "creation_date": "2025-01-03T12:56:38.684808+01:00",
        "daily_meal_count": 85,
        "yearly_meal_count": 28437,
        "line_ministry": null,
        "modification_date": "2026-01-02T13:53:43.237503+01:00",
        "logo": null,
        "sector_list": "Ecole primaire (maternelle et élémentaire)",
        "declaration_donnees_2021": false,
        "declaration_donnees_2022": false,
        "declaration_donnees_2023": false,
        "declaration_donnees_2024": false,
        "active_on_ma_cantine": true
      },
      "ministere": null,
      "region": "Bretagne",
      "ancienMinistere": null,
      "modifications": [
        {
          "champ": "yearly_meal_count",
          "label": "Couverts/an",
          "ancienne_valeur": 28961,
          "nouvelle_valeur": 28437
        }
      ]
    }
  ],
  "supprimes": [],
  "timestamp": "2026-01-04T06:43:13.562Z"
}